{
  "schemaVersion": 1,
  "id": "horde-resource-crops",
  "version": "${version}",
  "name": "Shale's Horde: Crystal Garden",
  "description": "",
  "authors": [],
  "contact": {},
  "license": "MIT",
  "icon": "assets/horde-resource-crops/icon.png",
  "environment": "*",
  "entrypoints": {
    "client": [
      "net.shale.horde.resource.crops.Client"
    ],
    "main": [
      "net.shale.horde.resource.crops.Main"
    ]
  },
  "mixins": [
    "horde-resource-crops.mixins.json"
  ],
  "depends": {
    "fabricloader": ">=0.13.3",
    "fabric": "*",
    "minecraft": "1.19"
  }
}
